Metadata-Version: 2.1
Name: oss2
Version: 2.7.0
Summary: Aliyun OSS (Object Storage Service) SDK
Home-page: http://oss.aliyun.com
Author: UNKNOWN
Author-email: UNKNOWN
License: UNKNOWN
Platform: UNKNOWN
Classifier: Development Status :: 5 - Production/Stable
Classifier: Intended Audience :: Developers
Classifier: License :: OSI Approved :: MIT License
Classifier: Operating System :: OS Independent
Classifier: Programming Language :: Python
Classifier: Programming Language :: Python :: 2
Classifier: Programming Language :: Python :: 2.6
Classifier: Programming Language :: Python :: 2.7
Classifier: Programming Language :: Python :: 3
Classifier: Programming Language :: Python :: 3.3
Classifier: Programming Language :: Python :: 3.4
Classifier: Programming Language :: Python :: 3.5
Requires-Dist: requests (!=2.9.0)
Requires-Dist: crcmod (>=1.7)
Requires-Dist: pycryptodome (>=3.4.7)
Requires-Dist: aliyun-python-sdk-kms (>=2.4.1)
Requires-Dist: aliyun-python-sdk-core (>=2.6.2)
